hawkesbook/__init__.py
hawkesbook/hawkes.py
hawkesbook-0.1.0.dist-info/LICENSE
hawkesbook-0.1.0.dist-info/METADATA
hawkesbook-0.1.0.dist-info/WHEEL
hawkesbook-0.1.0.dist-info/top_level.txt
hawkesbook-0.1.0.dist-info/RECORD
