Metadata-Version: 2.1
Name: hawkesbook
Version: 0.1.0
Summary: Hawkes process methods for inference, simulation, and related calculations
Home-page: https://github.com/Pat-Laub/hawkesbook
Author: Patrick Laub
Author-email: patrick.laub@gmail.com
License: MIT
Platform: UNKNOWN
Classifier: License :: OSI Approved :: MIT License
Classifier: Programming Language :: Python :: 3
Classifier: Programming Language :: Python :: 3.7
Classifier: Intended Audience :: Science/Research
Requires-Dist: numba
Requires-Dist: numpy
Requires-Dist: scipy
Requires-Dist: tqdm
